afacinemas_scraper/__init__.py
afacinemas_scraper/core/__init__.py
afacinemas_scraper/core/base.py
afacinemas_scraper/core/cinemas.py
afacinemas_scraper/core/filme.py
afacinemas_scraper/core/lancamentos.py
afacinemas_scraper/core/precos.py
afacinemas_scraper/core/programacao.py
afacinemas_scraper/main.py
afacinemas_scraper-1.5.1.dist-info/LICENSE
afacinemas_scraper-1.5.1.dist-info/METADATA
afacinemas_scraper-1.5.1.dist-info/WHEEL
afacinemas_scraper-1.5.1.dist-info/RECORD
