Metadata-Version: 2.1
Name: afacinemas-scraper
Version: 1.5.1
Summary: Ferramenta para raspagem de dados do site da rede Afa Cinemas
Home-page: https://github.com/douglasgusson/afacinemas-scraper
License: MIT
Keywords: python,scraping
Author: Douglas Gusson
Author-email: douglasgusson@gmail.com
Requires-Python: >=3.8,<4.0
Classifier: License :: OSI Approved :: MIT License
Classifier: Programming Language :: Python :: 3
Classifier: Programming Language :: Python :: 3.8
Classifier: Programming Language :: Python :: 3.9
Classifier: Programming Language :: Python :: 3.10
Classifier: Programming Language :: Python :: 3.11
Classifier: Programming Language :: Python :: 3.12
Requires-Dist: beautifulsoup4 (>=4.11.1,<5.0.0)
Requires-Dist: requests (>=2.28.1,<3.0.0)
Requires-Dist: requests-cache (>=0.9.5,<0.10.0)
Project-URL: Repository, https://github.com/douglasgusson/afacinemas-scraper
